miniworld_maze/__init__.py
miniworld_maze/core/__init__.py
miniworld_maze/core/constants.py
miniworld_maze/core/miniworld_gymnasium/README.md
miniworld_maze/core/miniworld_gymnasium/__init__.py
miniworld_maze/core/miniworld_gymnasium/base_env.py
miniworld_maze/core/miniworld_gymnasium/entities/__init__.py
miniworld_maze/core/miniworld_gymnasium/entities/agent.py
miniworld_maze/core/miniworld_gymnasium/entities/base_entity.py
miniworld_maze/core/miniworld_gymnasium/entities/objects.py
miniworld_maze/core/miniworld_gymnasium/entity_manager.py
miniworld_maze/core/miniworld_gymnasium/envs/__init__.py
miniworld_maze/core/miniworld_gymnasium/math.py
miniworld_maze/core/miniworld_gymnasium/objmesh.py
miniworld_maze/core/miniworld_gymnasium/occlusion_queries.py
miniworld_maze/core/miniworld_gymnasium/opengl.py
miniworld_maze/core/miniworld_gymnasium/params.py
miniworld_maze/core/miniworld_gymnasium/random.py
miniworld_maze/core/miniworld_gymnasium/rendering/__init__.py
miniworld_maze/core/miniworld_gymnasium/rendering/drawing.py
miniworld_maze/core/miniworld_gymnasium/rendering/framebuffer.py
miniworld_maze/core/miniworld_gymnasium/rendering/texture.py
miniworld_maze/core/miniworld_gymnasium/rendering_engine.py
miniworld_maze/core/miniworld_gymnasium/room.py
miniworld_maze/core/miniworld_gymnasium/texture_utils.py
miniworld_maze/core/miniworld_gymnasium/textures/airduct_grate_1.png
miniworld_maze/core/miniworld_gymnasium/textures/asphalt_1.png
miniworld_maze/core/miniworld_gymnasium/textures/beanpaste_1.png
miniworld_maze/core/miniworld_gymnasium/textures/beige_1.png
miniworld_maze/core/miniworld_gymnasium/textures/black_1.png
miniworld_maze/core/miniworld_gymnasium/textures/blueberry_1.png
miniworld_maze/core/miniworld_gymnasium/textures/brick_wall_1.png
miniworld_maze/core/miniworld_gymnasium/textures/cardboard_1.png
miniworld_maze/core/miniworld_gymnasium/textures/cardboard_2.png
miniworld_maze/core/miniworld_gymnasium/textures/cardboard_3.png
miniworld_maze-1.6.0.dist-info/WHEEL
miniworld_maze-1.6.0.dist-info/METADATA
miniworld_maze-1.6.0.dist-info/RECORD
