Metadata-Version: 2.3
Name: miniworld-maze
Version: 1.6.0
Summary: Multi-room maze environments from the DrStrategy paper. Provides NineRooms-v0, SpiralNineRooms-v0, and TwentyFiveRooms-v0 gymnasium environments.
Keywords: reinforcement-learning,environment,gymnasium,multi-room-maze,drstrategy,maze-navigation,partial-observability,3d-environments
Author: Tim Joseph
Author-email: Tim Joseph <tim@mctigger.com>
License: MIT License
Classifier: Development Status :: 4 - Beta
Classifier: Intended Audience :: Science/Research
Classifier: Intended Audience :: Developers
Classifier: Operating System :: OS Independent
Classifier: Programming Language :: Python :: 3
Classifier: Programming Language :: Python :: 3.8
Classifier: Programming Language :: Python :: 3.9
Classifier: Programming Language :: Python :: 3.10
Classifier: Programming Language :: Python :: 3.11
Classifier: Programming Language :: Python :: 3.12
Classifier: Topic :: Scientific/Engineering :: Artificial Intelligence
Classifier: Topic :: Software Development :: Libraries :: Python Modules
Classifier: Environment :: Console
Classifier: Typing :: Typed
Requires-Dist: gymnasium>=1.0.0,<2.0.0
Requires-Dist: numpy>=1.20.0,<3.0.0
Requires-Dist: opencv-python>=4.5.0,<5.0.0
Requires-Dist: pillow>=8.0.0,<11.0.0
Requires-Dist: pyopengl>=3.1.0,<4.0.0
Requires-Dist: pyglet>=1.5.0,<2.0.0
Requires-Dist: ruff>=0.1.0,<1.0.0 ; extra == 'dev'
Requires-Dist: build>=0.8.0,<2.0.0 ; extra == 'dev'
Requires-Dist: twine>=4.0.0,<6.0.0 ; extra == 'dev'
Requires-Dist: mujoco>=2.3.0,<4.0.0 ; extra == 'mujoco'
Requires-Python: >=3.8
Project-URL: Homepage, https://github.com/mctigger/miniworld-maze
Project-URL: Repository, https://github.com/mctigger/miniworld-maze
Project-URL: Bug Tracker, https://github.com/mctigger/miniworld-maze/issues
Project-URL: Documentation, https://github.com/mctigger/miniworld-maze#readme
Provides-Extra: dev
Provides-Extra: mujoco
